survte2/__init__.py
survte2/landxml_exporter.py
survte2/landxml_objects.py
survte2/landxml_parser.py
survte2/landxml_viewer.py
survte2/main.py
survte2-0.1.0.data/scripts/survte
survte2-0.1.0.dist-info/METADATA
survte2-0.1.0.dist-info/WHEEL
survte2-0.1.0.dist-info/top_level.txt
survte2-0.1.0.dist-info/RECORD
