Metadata-Version: 2.1
Name: survte2
Version: 0.1.0
Summary: A brief description of survte2
Home-page: https://github.com/samanii2/survte
Author: Jakob Samani
Author-email: Your Name <your.email@example.com>
License: MIT
Project-URL: Homepage, https://github.com/yourusername/survte2
Requires-Python: >=3.6
